qwiic_rfid.py
sparkfun_qwiic_rfid-2.0.0.dist-info/LICENSE
sparkfun_qwiic_rfid-2.0.0.dist-info/METADATA
sparkfun_qwiic_rfid-2.0.0.dist-info/WHEEL
sparkfun_qwiic_rfid-2.0.0.dist-info/top_level.txt
sparkfun_qwiic_rfid-2.0.0.dist-info/RECORD
